autocodec/__init__.py
autocodec/codec.py
autocodec/evit.py
autocodec/monarch.py
autocodec-0.2.2.dist-info/METADATA
autocodec-0.2.2.dist-info/WHEEL
autocodec-0.2.2.dist-info/top_level.txt
autocodec-0.2.2.dist-info/RECORD
